setup.py
gitProjectSpider/GUI.py
gitProjectSpider/__init__.py
gitProjectSpider/gitSpider.py
gitProjectSpider.egg-info/PKG-INFO
gitProjectSpider.egg-info/SOURCES.txt
gitProjectSpider.egg-info/dependency_links.txt
gitProjectSpider.egg-info/top_level.txt