Metadata-Version: 1.1
Name: gitProjectSpider
Version: 1.0
Summary: Python wrapper for the gitProjectSpider
Home-page: https://github.com/yishuihanhan/github-projects-downloader
Author: yishuihancheng
Author-email: yishuihancheng@qq.com
License: BSD
Keywords: github,project,downloader,gitProjectSpider
Platform: UNKNOWN
Classifier: Development Status :: 5 - Production/Stable
Classifier: Intended Audience :: Developers
Classifier: Natural Language :: English
Classifier: Operating System :: OS Independent
Classifier: Programming Language :: Python :: 2
Classifier: Topic :: Internet
Classifier: Topic :: Internet :: WWW/HTTP
